{
  "schemaVersion": 1,
  "id": "vvidgets",
  "version": "${version}",
  "name": "VVidgets",
  "description": "Custom widgets library, primarily used in screens.",
  "authors": [],
  "contact": {},
  "license": "All-Rights-Reserved",
  "icon": "assets/vvidgets/icon.png",
  "environment": "client",
  "entrypoints": {
    "client": [
      "net.velli.vvidgets.VVidgets"
    ]
  },
  "mixins": [
    "vvidgets.mixins.json"
  ],
  "depends": {
    "fabricloader": ">=${loader_version}",
    "fabric-api": "*",
    "minecraft": "${minecraft_version}"
  }
}
